test/fp_divider.v
module fp_divider
(
  input [31:0] A, B,
  input fp_clk,
  output[31:0] Out,
  input int_clk
);

//decode wires
wire a_sign, b_sign;
wire[7:0] a_exp, b_exp;
wire[22:0] a_frac, b_frac;
//calculation regs
reg start;
wire zero;
reg[47:0] b_reg, a_reg;
reg[24:0] Q;
//out wires
reg[22:0] out_frac;
wire[7:0] out_exp;
wire out_sign;

//decode the inputs
assign a_sign = A[31];
assign b_sign = B[31];
assign a_exp = A[30:23];
assign b_exp = B[30:23];
assign a_frac = A[22:0];
assign b_frac = B[22:0];


always @(posedge fp_clk) begin
  start <= 1'b1;
end

assign zero = (b_reg[47:24]==24'b0);

//calculate the quotient Q = A/B (timed to int_clk) by subtracting powers of the denominator B
always @(posedge int_clk) begin
  if (start===1) begin //Set initial values
    start <= 0;
    b_reg <= {1'b1, b_frac, 24'b0}; //
    a_reg <= {1'b1, a_frac, 24'b0}; //a_reg holds the remainder
    Q <= 0;
  end
  else begin
    if (zero === 0) begin //Check that the denominator hasn't bottomed out, which signals the end of the division.
      if(a_reg >= b_reg) begin
        a_reg <= a_reg-b_reg;
	Q <= (Q << 1) +1; //Make space for the next digit of the quotient
      end
      else begin
	Q <= Q << 1;
      end
      b_reg <= (b_reg >> 1); //right shift divides by two
    end
    //else begin //ending sequence, assign frac out and the exponent
    if (Q[24]===1) begin
	  out_frac <= Q[23:1];
    end
    else begin
	  out_frac <= Q[22:0];
    end
  end
end
//exponent logic
assign out_exp = a_exp - b_exp - Q[24] + 8'd127;
//sign bit logic
xor sign(out_sign, a_sign, b_sign);
//Concatenate the output values
assign Out = {out_sign, out_exp, out_frac};

endmodule

// module
// #(width = 32)
// (
// input clk,
// input start,
// input[width-1:0] A, B,
// output[2*width-1:0] Q
// );
// reg[width*2-1:0] a_reg, r_reg;

// always @(posedge clk) begin
//    if (start===1) begin
//   a_reg <= {A,31'b0};
//   r_reg <= {B,31'b0};
//   Q <= 63'b0;
//    end
//    else begin
//   if (a_reg>r_reg) begin
//      r_reg <= r_reg-a_reg;
//      Q <= Q+1;
//   end
//   a_reg >> 2;
//   Q << 2;
//    end
// end

test/fp_divider.t.v
module fpDividerTest();
reg [31:0] A, B;
wire [31:0] Out;
reg fp_clk, int_clk;
reg dutpassed;
integer i;

fp_divider dut(
  .fp_clk(fp_clk),
  .int_clk(int_clk),
  .A(A),
  .B(B),
  .Out(Out)
);

initial begin
  $dumpfile("test/waveform.vcd");
  $dumpvars(0, dut);
  dutpassed = 1'b1;

  // Setup
  fp_clk = 1'b0;
  #5
  fp_clk = 1'b1;
  int_clk = 1'b0;

  // Test Case 1 - Divide two positive integers
  A = 32'h41000000; // decimal 8
  B = 32'h40000000; // decimal 2
  for (i=0;i<50;i= i+1) begin
    #5 int_clk = 1'b1; #5 int_clk = 1'b0;
    if (i==25) begin
      fp_clk = 1'b0;
    end
  end

  if (Out !== 32'h40800000) begin // decimal 4
    dutpassed = 1'b0;
    $display("FP divider test case 1 failed. Read 32'h%h", Out);
  end

  fp_clk = 1'b1;

  // Test Case 2 - Divide an integer by 1
  A = 32'h41000000; // decimal 8
  B = 32'h3f800000; // decimal 1
  for (i=0;i<50;i= i+1) begin
    #5 int_clk = 1'b1; #5 int_clk = 1'b0;
    if (i==25) begin
      fp_clk = 1'b0;
    end
  end

  if (Out !== 32'h41000000) begin // decimal 8
    dutpassed = 1'b0;
    $display("FP divider test case 2 failed. Read 32'h%h", Out);
  end

  fp_clk = 1'b1;

  // Test Case 3 - Divide a positive integer by a negative integer
  A = 32'h41000000; // decimal 8
  B = 32'hc0000000; // decimal -2
  for (i=0;i<50;i= i+1) begin
    #5 int_clk = 1'b1; #5 int_clk = 1'b0;
    if (i==25) begin
      fp_clk = 1'b0;
    end
  end

  if (Out !== 32'hc0800000) begin // decimal -4
    dutpassed = 1'b0;
    $display("FP divider test case 3 failed. Read 32'h%h", Out);
  end

  fp_clk = 1'b1;

  // Test Case 4 - Divide two negative integers
  A = 32'hc1000000; // decimal -8
  B = 32'hc0000000; // decimal -2
  for (i=0;i<50;i= i+1) begin
    #5 int_clk = 1'b1; #5 int_clk = 1'b0;
    if (i==25) begin
      fp_clk = 1'b0;
    end
  end

  if (Out !== 32'h40800000) begin // decimal 4
    dutpassed = 1'b0;
    $display("FP divider test case 4 failed. Read 32'h%h", Out);
  end

  fp_clk = 1'b1;

  // Test Case 5 - Divide two positive decimals
  A = 32'h415c0000; // decimal 13.75
  B = 32'h40b00000; // decimal 5.5
  for (i=0;i<50;i= i+1) begin
    #5 int_clk = 1'b1; #5 int_clk = 1'b0;
    if (i==25) begin
      fp_clk = 1'b0;
    end
  end

  if (Out !== 32'h40200000) begin // decimal 2.5
    dutpassed = 1'b0;
    $display("FP divider test case 5 failed. Read 32'h%h", Out);
  end

  fp_clk = 1'b1;

  // Test Case 6 - Divide a positive decimal by 1
  A = 32'h415c0000; // decimal 13.75
  B = 32'h3f800000; // decimal 1
  for (i=0;i<50;i= i+1) begin
    #5 int_clk = 1'b1; #5 int_clk = 1'b0;
    if (i==25) begin
      fp_clk = 1'b0;
    end
  end

  if (Out !== 32'h415c0000) begin // decimal 13.75
    dutpassed = 1'b0;
    $display("FP divider test case 6 failed. Read 32'h%h", Out);
  end

  fp_clk = 1'b1;

  // Test Case 7 - Divide a positive decimal by a negative decimal
  A = 32'h415c0000; // decimal 13.75
  B = 32'hc0b00000; // decimal -5.5
  for (i=0;i<50;i= i+1) begin
    #5 int_clk = 1'b1; #5 int_clk = 1'b0;
    if (i==25) begin
      fp_clk = 1'b0;
    end
  end

  if (Out !== 32'hc0200000) begin // decimal -2.5
    dutpassed = 1'b0;
    $display("FP divider test case 7 failed. Read 32'h%h", Out);
  end

  fp_clk = 1'b1;

  // Test Case 8 - Divide two negative decimals
  A = 32'hc15c0000; // decimal -13.75
  B = 32'hc0b00000; // decimal -5.5
  for (i=0;i<50;i= i+1) begin
    #5 int_clk = 1'b1; #5 int_clk = 1'b0;
    if (i==25) begin
      fp_clk = 1'b0;
    end
  end

  if (Out !== 32'h40200000) begin // decimal 2.5
    dutpassed = 1'b0;
    $display("FP divider test case 8 failed. Read 32'h%h", Out);
  end

  $display("FP divider passed?: %b", dutpassed);
end

endmodule

test/dump.vcd
$date
	Mon Dec 07 12:11:23 2015
$end
$version
	ModelSim Version 10.4a
$end
$timescale
	1ns
$end

$scope module fpDividerTest $end

$scope module dut $end
$var wire 1 ! A [31] $end
$var wire 1 " A [30] $end
$var wire 1 # A [29] $end
$var wire 1 $ A [28] $end
$var wire 1 % A [27] $end
$var wire 1 & A [26] $end
$var wire 1 ' A [25] $end
$var wire 1 ( A [24] $end
$var wire 1 ) A [23] $end
$var wire 1 * A [22] $end
$var wire 1 + A [21] $end
$var wire 1 , A [20] $end
$var wire 1 - A [19] $end
$var wire 1 . A [18] $end
$var wire 1 / A [17] $end
$var wire 1 0 A [16] $end
$var wire 1 1 A [15] $end
$var wire 1 2 A [14] $end
$var wire 1 3 A [13] $end
$var wire 1 4 A [12] $end
$var wire 1 5 A [11] $end
$var wire 1 6 A [10] $end
$var wire 1 7 A [9] $end
$var wire 1 8 A [8] $end
$var wire 1 9 A [7] $end
$var wire 1 : A [6] $end
$var wire 1 ; A [5] $end
$var wire 1 < A [4] $end
$var wire 1 = A [3] $end
$var wire 1 > A [2] $end
$var wire 1 ? A [1] $end
$var wire 1 @ A [0] $end
$var wire 1 A B [31] $end
$var wire 1 B B [30] $end
$var wire 1 C B [29] $end
$var wire 1 D B [28] $end
$var wire 1 E B [27] $end
$var wire 1 F B [26] $end
$var wire 1 G B [25] $end
$var wire 1 H B [24] $end
$var wire 1 I B [23] $end
$var wire 1 J B [22] $end
$var wire 1 K B [21] $end
$var wire 1 L B [20] $end
$var wire 1 M B [19] $end
$var wire 1 N B [18] $end
$var wire 1 O B [17] $end
$var wire 1 P B [16] $end
$var wire 1 Q B [15] $end
$var wire 1 R B [14] $end
$var wire 1 S B [13] $end
$var wire 1 T B [12] $end
$var wire 1 U B [11] $end
$var wire 1 V B [10] $end
$var wire 1 W B [9] $end
$var wire 1 X B [8] $end
$var wire 1 Y B [7] $end
$var wire 1 Z B [6] $end
$var wire 1 [ B [5] $end
$var wire 1 \ B [4] $end
$var wire 1 ] B [3] $end
$var wire 1 ^ B [2] $end
$var wire 1 _ B [1] $end
$var wire 1 ` B [0] $end
$var wire 1 a fp_clk $end
$var wire 1 b Out [31] $end
$var wire 1 c Out [30] $end
$var wire 1 d Out [29] $end
$var wire 1 e Out [28] $end
$var wire 1 f Out [27] $end
$var wire 1 g Out [26] $end
$var wire 1 h Out [25] $end
$var wire 1 i Out [24] $end
$var wire 1 j Out [23] $end
$var wire 1 k Out [22] $end
$var wire 1 l Out [21] $end
$var wire 1 m Out [20] $end
$var wire 1 n Out [19] $end
$var wire 1 o Out [18] $end
$var wire 1 p Out [17] $end
$var wire 1 q Out [16] $end
$var wire 1 r Out [15] $end
$var wire 1 s Out [14] $end
$var wire 1 t Out [13] $end
$var wire 1 u Out [12] $end
$var wire 1 v Out [11] $end
$var wire 1 w Out [10] $end
$var wire 1 x Out [9] $end
$var wire 1 y Out [8] $end
$var wire 1 z Out [7] $end
$var wire 1 { Out [6] $end
$var wire 1 | Out [5] $end
$var wire 1 } Out [4] $end
$var wire 1 ~ Out [3] $end
$var wire 1 !! Out [2] $end
$var wire 1 "! Out [1] $end
$var wire 1 #! Out [0] $end
$var wire 1 $! int_clk $end
$var wire 1 %! a_sign $end
$var wire 1 &! b_sign $end
$var wire 1 '! a_exp [7] $end
$var wire 1 (! a_exp [6] $end
$var wire 1 )! a_exp [5] $end
$var wire 1 *! a_exp [4] $end
$var wire 1 +! a_exp [3] $end
$var wire 1 ,! a_exp [2] $end
$var wire 1 -! a_exp [1] $end
$var wire 1 .! a_exp [0] $end
$var wire 1 /! b_exp [7] $end
$var wire 1 0! b_exp [6] $end
$var wire 1 1! b_exp [5] $end
$var wire 1 2! b_exp [4] $end
$var wire 1 3! b_exp [3] $end
$var wire 1 4! b_exp [2] $end
$var wire 1 5! b_exp [1] $end
$var wire 1 6! b_exp [0] $end
$var wire 1 7! a_frac [22] $end
$var wire 1 8! a_frac [21] $end
$var wire 1 9! a_frac [20] $end
$var wire 1 :! a_frac [19] $end
$var wire 1 ;! a_frac [18] $end
$var wire 1 <! a_frac [17] $end
$var wire 1 =! a_frac [16] $end
$var wire 1 >! a_frac [15] $end
$var wire 1 ?! a_frac [14] $end
$var wire 1 @! a_frac [13] $end
$var wire 1 A! a_frac [12] $end
$var wire 1 B! a_frac [11] $end
$var wire 1 C! a_frac [10] $end
$var wire 1 D! a_frac [9] $end
$var wire 1 E! a_frac [8] $end
$var wire 1 F! a_frac [7] $end
$var wire 1 G! a_frac [6] $end
$var wire 1 H! a_frac [5] $end
$var wire 1 I! a_frac [4] $end
$var wire 1 J! a_frac [3] $end
$var wire 1 K! a_frac [2] $end
$var wire 1 L! a_frac [1] $end
$var wire 1 M! a_frac [0] $end
$var wire 1 N! b_frac [22] $end
$var wire 1 O! b_frac [21] $end
$var wire 1 P! b_frac [20] $end
$var wire 1 Q! b_frac [19] $end
$var wire 1 R! b_frac [18] $end
$var wire 1 S! b_frac [17] $end
$var wire 1 T! b_frac [16] $end
$var wire 1 U! b_frac [15] $end
$var wire 1 V! b_frac [14] $end
$var wire 1 W! b_frac [13] $end
$var wire 1 X! b_frac [12] $end
$var wire 1 Y! b_frac [11] $end
$var wire 1 Z! b_frac [10] $end
$var wire 1 [! b_frac [9] $end
$var wire 1 \! b_frac [8] $end
$var wire 1 ]! b_frac [7] $end
$var wire 1 ^! b_frac [6] $end
$var wire 1 _! b_frac [5] $end
$var wire 1 `! b_frac [4] $end
$var wire 1 a! b_frac [3] $end
$var wire 1 b! b_frac [2] $end
$var wire 1 c! b_frac [1] $end
$var wire 1 d! b_frac [0] $end
$var reg 1 e! start $end
$var wire 1 f! zero $end
$var reg 48 g! b_reg [47:0] $end
$var reg 48 h! a_reg [47:0] $end
$var reg 25 i! Q [24:0] $end
$var reg 23 j! out_frac [22:0] $end
$var wire 1 k! out_exp [7] $end
$var wire 1 l! out_exp [6] $end
$var wire 1 m! out_exp [5] $end
$var wire 1 n! out_exp [4] $end
$var wire 1 o! out_exp [3] $end
$var wire 1 p! out_exp [2] $end
$var wire 1 q! out_exp [1] $end
$var wire 1 r! out_exp [0] $end
$var wire 1 s! out_sign $end
$upscope $end
$upscope $end
$enddefinitions $end
#0
$dumpvars
xe!
bx g!
bx h!
bx i!
bx j!
x#!
x"!
x!!
x~
x}
x|
x{
xz
xy
xx
xw
xv
xu
xt
xs
xr
xq
xp
xo
xn
xm
xl
xk
xj
xi
xh
xg
xf
xe
xd
xc
xb
x%!
x&!
x.!
x-!
x,!
x+!
x*!
x)!
x(!
x'!
x6!
x5!
x4!
x3!
x2!
x1!
x0!
x/!
xM!
xL!
xK!
xJ!
xI!
xH!
xG!
xF!
xE!
xD!
xC!
xB!
xA!
x@!
x?!
x>!
x=!
x<!
x;!
x:!
x9!
x8!
x7!
xd!
xc!
xb!
xa!
x`!
x_!
x^!
x]!
x\!
x[!
xZ!
xY!
xX!
xW!
xV!
xU!
xT!
xS!
xR!
xQ!
xP!
xO!
xN!
xf!
xr!
xq!
xp!
xo!
xn!
xm!
xl!
xk!
xs!
x`
x_
x^
x]
x\
x[
xZ
xY
xX
xW
xV
xU
xT
xS
xR
xQ
xP
xO
xN
xM
xL
xK
xJ
xI
xH
xG
xF
xE
xD
xC
xB
xA
x@
x?
x>
x=
x<
x;
x:
x9
x8
x7
x6
x5
x4
x3
x2
x1
x0
x/
x.
x-
x,
x+
x*
x)
x(
x'
x&
x%
x$
x#
x"
x!
x$!
0a
$end
#5
0`
0_
0^
0]
0\
0[
0Z
0Y
0X
0W
0V
0U
0T
0S
0R
0Q
0P
0O
0N
0M
0L
0K
0J
0I
0H
0G
0F
0E
0D
0C
1B
0A
0@
0?
0>
0=
0<
0;
0:
09
08
07
06
05
04
03
02
01
00
0/
0.
0-
0,
0+
0*
0)
1(
0'
0&
0%
0$
0#
1"
0!
0&!
0.!
1-!
0,!
0+!
0*!
0)!
0(!
1'!
0M!
0L!
0K!
0J!
0I!
0H!
0G!
0F!
0E!
0D!
0C!
0B!
0A!
0@!
0?!
0>!
0=!
0<!
0;!
0:!
09!
08!
07!
06!
05!
04!
03!
02!
01!
00!
1/!
0d!
0c!
0b!
0a!
0`!
0_!
0^!
0]!
0\!
0[!
0Z!
0Y!
0X!
0W!
0V!
0U!
0T!
0S!
0R!
0Q!
0P!
0O!
0N!
0%!
0s!
0b
1a
0$!
1e!
#10
1$!
0e!
b100000000000000000000000000000000000000000000000 g!
b100000000000000000000000000000000000000000000000 h!
b0 i!
0f!
1r!
0q!
0p!
0o!
0n!
0m!
0l!
1k!
1j
0i
0h
0g
0f
0e
0d
1c
#15
0$!
#20
1$!
b0 h!
b1 i!
b10000000000000000000000000000000000000000000000 g!
b0 j!
0#!
0"!
0!!
0~
0}
0|
0{
0z
0y
0x
0w
0v
0u
0t
0s
0r
0q
0p
0o
0n
0m
0l
0k
#25
0$!
#30
1$!
b10 i!
b1000000000000000000000000000000000000000000000 g!
b1 j!
1#!
#35
0$!
#40
1$!
b100 i!
b100000000000000000000000000000000000000000000 g!
b10 j!
0#!
1"!
#45
0$!
#50
1$!
b1000 i!
b10000000000000000000000000000000000000000000 g!
b100 j!
0"!
1!!
#55
0$!
#60
1$!
b10000 i!
b1000000000000000000000000000000000000000000 g!
b1000 j!
0!!
1~
#65
0$!
#70
1$!
b100000 i!
b100000000000000000000000000000000000000000 g!
b10000 j!
0~
1}
#75
0$!
#80
1$!
b1000000 i!
b10000000000000000000000000000000000000000 g!
b100000 j!
0}
1|
#85
0$!
#90
1$!
b10000000 i!
b1000000000000000000000000000000000000000 g!
b1000000 j!
0|
1{
#95
0$!
#100
1$!
b100000000 i!
b100000000000000000000000000000000000000 g!
b10000000 j!
0{
1z
#105
0$!
#110
1$!
b1000000000 i!
b10000000000000000000000000000000000000 g!
b100000000 j!
0z
1y
#115
0$!
#120
1$!
b10000000000 i!
b1000000000000000000000000000000000000 g!
b1000000000 j!
0y
1x
#125
0$!
#130
1$!
b100000000000 i!
b100000000000000000000000000000000000 g!
b10000000000 j!
0x
1w
#135
0$!
#140
1$!
b1000000000000 i!
b10000000000000000000000000000000000 g!
b100000000000 j!
0w
1v
#145
0$!
#150
1$!
b10000000000000 i!
b1000000000000000000000000000000000 g!
b1000000000000 j!
0v
1u
#155
0$!
#160
1$!
b100000000000000 i!
b100000000000000000000000000000000 g!
b10000000000000 j!
0u
1t
#165
0$!
#170
1$!
b1000000000000000 i!
b10000000000000000000000000000000 g!
b100000000000000 j!
0t
1s
#175
0$!
#180
1$!
b10000000000000000 i!
b1000000000000000000000000000000 g!
b1000000000000000 j!
0s
1r
#185
0$!
#190
1$!
b100000000000000000 i!
b100000000000000000000000000000 g!
b10000000000000000 j!
0r
1q
#195
0$!
#200
1$!
b1000000000000000000 i!
b10000000000000000000000000000 g!
b100000000000000000 j!
0q
1p
#205
0$!
#210
1$!
b10000000000000000000 i!
b1000000000000000000000000000 g!
b1000000000000000000 j!
0p
1o
#215
0$!
#220
1$!
b100000000000000000000 i!
b100000000000000000000000000 g!
b10000000000000000000 j!
0o
1n
#225
0$!
#230
1$!
b1000000000000000000000 i!
b10000000000000000000000000 g!
b100000000000000000000 j!
0n
1m
#235
0$!
#240
1$!
b10000000000000000000000 i!
b1000000000000000000000000 g!
b1000000000000000000000 j!
0m
1l
#245
0$!
#250
1$!
b100000000000000000000000 i!
b100000000000000000000000 g!
b10000000000000000000000 j!
1f!
0l
1k
#255
0$!
#260
1$!
b0 j!
0k
